nkdms/__init__.py
nkdms/main.py
nkdms-0.1.0.dist-info/METADATA
nkdms-0.1.0.dist-info/WHEEL
nkdms-0.1.0.dist-info/top_level.txt
nkdms-0.1.0.dist-info/RECORD
