Metadata-Version: 2.1
Name: nkdms
Version: 0.1.0
Summary: Lite document management system  library
Home-page: UNKNOWN
Author: nikolakadic
Author-email: UNKNOWN
License: MIT
Platform: UNKNOWN
